envpp/__init__.py
envpp/__main__.py
envpp/_item.py
envpp/_item.template
envpp/api/__init__.py
envpp/api/resources/__init__.py
envpp/api/resources/authentication.py
envpp/api/resources/items.py
envpp/api/resources/resource.py
envpp/api/structs/__init__.py
envpp/api/structs/error.py
envpp/api/structs/item.py
envpp/api/structs/sign.py
envpp/cli/__init__.py
envpp/cli/api/__init__.py
envpp/cli/api/auth.py
envpp/cli/api/items.py
envpp/common.py
envpp/envpp.py
envpp/token.txt
envpp-1.0.1.dist-info/METADATA
envpp-1.0.1.dist-info/WHEEL
envpp-1.0.1.dist-info/RECORD
